Metadata-Version: 2.1
Name: kdc-pipline
Version: 0.0.1
Summary: A very basic calculator
Home-page: 
Author: Johannes Kanthak
Author-email: johannes.kanthak@kdc-solutions.de
License: MIT
Keywords: Pipeline
Classifier: Development Status :: 5 - Production/Stable
Classifier: Intended Audience :: Education
Classifier: Operating System :: Microsoft :: Windows :: Windows 10
Classifier: License :: OSI Approved :: MIT License
Classifier: Programming Language :: Python :: 3
